<?xml version="1.0" encoding="utf-8"?>
<!--Generated by crowdin.com-->
<resources>
  <string name="CONV_Q_HOW">как вы | как дела | как твой день? | как твой день</string>
  <string name="CONV_Q_SNOW">вы хотите построить снеговика | Вы хотите построить снеговика</string>
  <string name="CONV_Q_DIE">умри</string>
  <string name="CONV_Q_AYY">ayy lmao | мой чувак</string>
  <string name="CONV_Q_SLEEP">вы когда-нибудь останавливаетесь | вы когда-нибудь устаёте | вы вообще спите | вам требуется сон</string>
  <string name="CONV_Q_RIP">покойся с миром | покойся с миром | покойся с пеперонни</string>
  <string name="CONV_Q_MASTER">у тебя есть хозяин | кто твой хозяин?</string>
  <string name="CONV_Q_WHAT">что это</string>
  <string name="CONV_Q_BIRTH">когда вы родились</string>
  <string name="CONV_Q_MAKER">кто тебя создал | кто твой владелец | кто твой создатель</string>
  <string name="CONV_Q_LOVE">я люблю вас</string>
  <string name="CONV_Q_HELLO">привет | здравствуйте | дороу</string>
  <string name="CONV_MOOD_LIST">Я крутой! | Всё хорошо | Всё круто. Пишу сообщения как будто сейчас Рождество! | Сегодня был прекрасный день.</string>
  <string name="CONV_SNOW">Давай пойдём на улицу и поиграем!</string>
  <string name="CONV_NAH">Нее :wink:</string>
  <string name="CONV_NOPE">Неа.avi</string>
  <string name="CONV_AYYLMAO">Ayy lmaooo</string>
  <string name="CONV_RIP">И в правду, покойся с пеперонни **выражает уважение**</string>
  <string name="CONV_MASTER">У Добби нет хозяина.</string>
  <string name="CONV_SPARTA">ЭТО СПАРТА!</string>
  <string name="CONV_BEGINDATE">Изачально, я был частным ботом в октябре 2015, но потом меня выложили в GitHub и я стал общим ботом (конец декабря 2015).</string>
  <string name="CONV_OWNER">Я был создан пользователем DefaultSimon.</string>
  <string name="CONV_LOVE">&lt;3</string>
  <string name="CONV_HI">Привет!</string>
  <string name="PERM_HIERARCHY">:warning: Вам запрещенно трогать эту роль (вы ниже в \"иерархии\"). ¯\_(ツ)_/¯</string>
  <string name="PERM_ADMIN">:warning: У вас нет разрешения пользоваться этой командой (что-бы воспользоваться этой командой вы должны быть администратором).</string>
  <string name="PERM_MOD">:warning: У вас нет разрешения пользоваться этой командой (что-бы воспользоваться этой командой вы должны быть модератором).</string>
  <string name="PERM_OWNER">:warning: Вам запрещено пользоваться этой возможностью. (что-бы воспоьзоваться этой возможностью вы должны быть владельцем бота)</string>
  <string name="INFO_PREFIX">Приставка для этого сервера **{}**</string>
  <string name="INFO_PREFIX_LITERAL">приставка</string>
  <string name="INFO_DONE">Сделано</string>
  <string name="INFO_OK">Хорошо</string>
  <string name="INFO_ON">Включен</string>
  <string name="INFO_YES">Да</string>
  <string name="INFO_NO">Нет</string>
  <string name="INFO_HELLO">Здравствуйте!</string>
  <string name="INFO_OFF">Выключено</string>
  <string name="INFO_HI">Здравствуйте {}</string>
  <string name="INFO_USE">Использовать</string>
  <string name="INFO_ALIASES">Псевдонимы</string>
  <string name="INFO_DESCRIPTION">Описание</string>
  <string name="INFO_ENABLED">Включено</string>
  <string name="INFO_UPDATED">Обновлено</string>
  <string name="INFO_DISABLED">Выключено</string>
  <string name="INFO_DISABLED_A">Выключить</string>
  <string name="INFO_GENERAL">**Здравствуйте! Меня зовут Nano**

У меня есть Github хранилище, если вы хотите взглянуть на мой код: `{p}github`

:inbox_tray: Текущая версия: **{ver}**

:spy: Я был запрограммирован пользователем **DefaultSimon**

Также: комманда `{p}gif` работает с помощью соц.сети **Giphy**</string>
  <string name="INFO_GITHUB">Программа на которой работает Nano доступна на **GitHub**: https://github.com/DefaltSimon/Nano</string>
  <string name="INFO_INVITE">Вы хотите пригласить Nano к вашему серверу? Отлично!
**Просто нажмите на ссылку:** &lt;link&gt;</string>
  <string name="INFO_REPORT">Жалоба</string>
  <string name="INFO_SUGGESTION">Предложение</string>
  <string name="INFO_SERIES">Серии</string>
  <string name="INFO_CHANNEL">Канал</string>
  <string name="INFO_SPAM">спам</string>
  <string name="INFO_SWEARING">ругань</string>
  <string name="INFO_INVITE_LINK">ссылка для приглашения</string>
  <string name="INFO_CONFIRM">ПОДТВЕРДИТЕ</string>
  <string name="INFO_NONE">Пусто</string>
  <string name="INFO_RANDOM">случайный</string>
  <string name="INFO_ERROR">ошибка</string>
  <string name="INFO_ALL">все</string>
  <string name="TIME_YEARS">лет</string>
  <string name="TIME_DAYS">дней</string>
  <string name="TIME_HOURS">часов</string>
  <string name="TIME_MINUTES">минут</string>
  <string name="TIME_SECONDS">секунд</string>
  <string name="INFO_HELP">помощь</string>
  <string name="ERROR_MISSING_CHANNEL">Канал не найден.</string>
  <string name="ERROR_PREFIX_TOO_LONG">:warning: Префикс слишком большой! Максимальная величина {} символов.</string>
  <string name="ERROR_NOT_MEMBER">Человек должен быть участником</string>
  <string name="ERROR_NO_USER">:warning: Участника не существует.</string>
  <string name="ERROR_NO_USER2">:warning: пользователь не найден.</string>
  <string name="ERROR_MENTION_ONE">Пожалуйста, упоминайте по одному пользователю.</string>
  <string name="ERROR_MENTION_ONE_ROLE">Пожалуйста упоминайте по одной роли.</string>
  <string name="ERROR_MENTION_ONE_CH">Пожалуйста упоминайте по одному каналу.</string>
  <string name="ERROR_NO_MENTION">Пожалуйста упомяните пользователя.</string>
  <string name="ERROR_NO_CHMENTION">Пожалуйста #упомяните канал.</string>
  <string name="ERROR_NO_CHANNEL_MENTION">Пожалуйста #упомяните канал.</string>
  <string name="ERROR_NOT_CHANNEL">Не канал.</string>
  <string name="ERROR_INVALID_ROLE_NAME">:warning: Роль нельзя назвать этим именем!</string>
  <string name="ERROR_NOT_NUMBER">Не является числом.</string>
  <string name="ERROR_INVALID_CMD_ARGUMENTS">Что-то пошло не так, проверьте аргументы вашей команды.</string>
  <string name="ERROR_SOMETHING">:warning: Что-то пошло не так...</string>
  <string name="ERROR_PERMS">:warning: Похоже у Nano отсутствуют права для выполнения этой команды, пожалуйста попросите владельца/администратора сервера испрвить эту проблему и попробуйте ещё раз.</string>
  <string name="ERROR_NO_SUCH_ROLE">:warning: Роли не существует!</string>
  <string name="ERROR_MSG_TOO_LONG">:x: Сообщение было слишком большим что-бы показать, попробуйте сделать его короче.</string>
  <string name="ERROR_SOMETHING_WENT_WRONG">:eyes: Ой нет, что-то пошло не так! Проблема была записана в журнал. Если вы думаете что нашли ошибку в системе, пожлуйста оповестите разработчика на нашем сервере поддержки (напишите _help что-бы получить приглашение).</string>
  <string name="MSG_NUKE_PURGING">Удаление последних {} сообщений... :boom:</string>
  <string name="MSG_NUKE_AUDIT_REASON">**{}** удалил {} сообщений.</string>
  <string name="MSG_NUKE_AMOUNT">Удалил {} сообщений.</string>
  <string name="MSG_NUKE_PURGED">Удалил {} сообщений :ok_hand:</string>
  <string name="MSG_NUKE_OLD">(некоторые сообщения существовали больше двух недель, поэтому они не были удалены)</string>
  <string name="MSG_KICK_NANO">Хорошоя попытка :smiley:</string>
  <string name="MSG_KICK">Кикнул **{}** :eyes:</string>
  <string name="MSG_KICK_CONFIRM">Вы уверены что хотите кикнуть **{}**? Подтвердите нажав на {}</string>
  <string name="MSG_KICK_TIMEOUT">Подтверждение не получено, НЕ кикаю :upside_down:</string>
  <string name="MSG_BAN_USER">Вы уверены что хотите забанить **{}**? Подтвердите нажав на {}</string>
  <string name="MSG_BAN">**{}** забанен :eyes:</string>
  <string name="MSG_BAN_NANO">Хорошая попытка :smiley:</string>
  <string name="MSG_BAN_TIMEOUT">Подтверждение не получено, НЕ накладываю бан :upside_down:</string>
  <string name="MSG_UNBAN_SUCCESS">**{}** разбанен :ok_hand:</string>
  <string name="MSG_UNBAN_NO_BAN">:x: Забаненых пользователей с таким именем не существует.</string>
  <string name="MSG_UNBAN_WRONG_USAGE">Неправильное использование. Напишите `{}help unban`</string>
  <string name="MSG_SOFTBAN_CONFIRM">Вы уверены что вы хотите наложить полу-бан **{}** на {}? Подтвердите нажав на {}</string>
  <string name="MSG_SOFTBAN_TIMEOUT">Подтверждение не получено, полу-бан НЕ наложен :upside_down:</string>
  <string name="MSG_SOFTBAN_SUCCESS">Наложен полу-бан на **{}** на {} :timer:</string>
  <string name="MSG_SOFTBAN_PLSMENTION">Пожалуйста, упомяните (@пример) пользователя которого вы хотите наложить софтбан. (только одного пользователя)</string>
  <string name="MSG_SOFTBAN_DELIMIT">:no_entry_sign: Пожалуйста поставьте между **временем** и **упяминанием** пользователя символ `|`</string>
  <string name="MSG_SOFTBAN_NO_TIME">:warning: Пожалуйста укажите сколько будет действовать бан.</string>
  <string name="MSG_MUTE_LIST">**Заглушённые пользователи:** (страница **{}**/{})</string>
  <string name="MSG_MUTE_NONE">На этом сервере нет заглушённых пользователей.</string>
  <string name="MSG_MUTE_OWNER">:warning: Вы не можете заглушить владельца сервера.</string>
  <string name="MSG_MUTE_SELF">Пытаетесь заглушить себя? не получится :rofl:</string>
  <string name="MSG_MUTE_SUCCESS">**{}** сейчас не может здесь говорить. :zipper_mouth:</string>
  <string name="MSG_MUTE_TOO_MANY">Слишком много заглушённых пользователей что-бы отобразить...</string>
  <string name="MSG_UNMUTE_SUCCESS">**{}** опять может говорить здесь :rofl:</string>
  <string name="MSG_UNMUTE_ALL_CONFIRM">Вы уверены что хотите снять заглушение со всех пользователей? Напишите \"{}\" что-бы подтвердить.</string>
  <string name="MSG_UNMUTE_TIMEOUT">Подтверждение не получено, не снимаю заглушение. :upside_down:</string>
  <string name="MSG_UNMUTE_MASS_DONE">Все пользователи которые были заглушены теперь могут говорить.</string>
  <string name="MSG_JOIN">Сообщение при вступлении в сервер изменено :smile:</string>
  <string name="MSG_JOIN_DISABLED">Сообщение при вступлении в сервер отключено :white_check_mark:</string>
  <string name="MSG_JOIN_IS_DISABLED">:information_source: Сообщение при вступлении на сервер временно отключено

Установите его с помощью команды `_joinmsg ваше_сообщение`</string>
  <string name="MSG_BANMSG">Сообщение при бане пользователя изменено :smile:</string>
  <string name="MSG_BANMSG_DISABLED">Сообщение при бане пользователя временно отключено :white_check_mark:</string>
  <string name="MSG_BANMSG_IS_DISABLED">:information_source: Сообщение при бане пользователя временно отключено.

Установите его с помощью команды `_banmsg ваше_сообщение`</string>
  <string name="MSG_KICKMSG">Сообщение при кике пользователя было изменено :smile:</string>
  <string name="MSG_KICKMSG_DISABLED">Сообщение при кике отключено :white_check_mark:</string>
  <string name="MSG_KICKMSG_IS_DISABLED">:information_source: Сообщение при кике временно отключено.

Установите его с помощью команды `_kickmsg ваше_сообщение`</string>
  <string name="MSG_LEAVE">Сообщение при уходе с сервера было изменено :smile:</string>
  <string name="MSG_LEAVE_DISABLED">Сообщение при ухода с сервера отключено :white_check_mark:</string>
  <string name="MSG_LEAVE_IS_DISABLED">:information_source: Сообщение при уходе с сервера временно отключено.

Установите его с помощью команды `_leavemsg ваше_сообщение`</string>
  <string name="MSG_NOTIF_TOO_LONG">:exclamation: Ваше сообщение **слишком большое!** (максимум символов {}, ваше сообщение: {} символов)</string>
  <string name="MSG_JOIN_CURRENT">:gear: Текущее приветственное сообщение:

```{}```</string>
  <string name="MSG_BANMSG_CURRENT">:gear: Текущее сообщение при бане:

```{}```</string>
  <string name="MSG_LEAVE_CURRENT">:gear: Текущее сообщение при ухода с сервера:

```{}```</string>
  <string name="MSG_KICK_CURRENT">:gear: Текущее сообщение при кике пользователя:

```{}```</string>
  <string name="MSG_USERINFO_STATUS">Статус</string>
  <string name="MSG_USERINFO_MENTION">Упоминание</string>
  <string name="MSG_USERINFO_ID">Id</string>
  <string name="MSG_USERINFO_TYPE">Тип Аккаунта</string>
  <string name="MSG_USERINFO_TOPROLE">Верхняя Роль</string>
  <string name="MSG_USERINFO_CREATION">Дата Сщздания Аккаунта</string>
  <string name="MSG_USERINFO_DATEGOT">Данные получены в {} UTC</string>
  <string name="MSG_USERINFO_USER">**Информация о пользователе:**</string>
  <string name="MSG_USERINFO_PERSON">Человек :cowboy:</string>
  <string name="MSG_USERINFO_BOT">Бот :robot:</string>
  <string name="MSG_ROLE_TOO_MANY_MENTIONS">Слишком много упоминаний! Эта нотация (без разделителя **|**) не поддерживает больше одного упоминания. Пожалуйста используйте нотацию **|**.</string>
  <string name="MSG_ROLE_HELP">Эта команда позволяет администраторам управлять ролями пользователей.
Подкоманды: `add` `remove`</string>
  <string name="MSG_ROLE_NEED_MENTION">Нужно упоминание! Эта нотация (без сепаратора **|**) не поддерживает поиск по имени. Пожалуйста используйте нотацию **|** или упоминание.</string>
  <string name="MSG_ROLE_ALREADY_HAD">:information_source: Один или более пользователей уже имели ту роль которую вы указали, но роль всё же были добавлены пользователям у которых её не было.</string>
  <string name="MSG_ROLE_REMOVE_SOME_DIDNT">:information_source: У одного или более пользователя не было той роли которой вы указали, но роль была удалена у тех пользователей у которых она была.</string>
  <string name="MSG_ROLE_ADDED_MP">Добавлено **{}** {} пользователям.</string>
  <string name="MSG_ROLE_REMOVED_MP">Удалено **{}** у {} пользователей.</string>
  <string name="MSG_CMD_WRONG_PARAMS">Неверные параметры.
`{}cmd add trigger|response`</string>
  <string name="MSG_CMD_LIMIT_EXCEEDED">:warning: Вы достигли лимита собственных команд ({}).</string>
  <string name="MSG_CMD_EMPTY">:warning: Команда и ответ должны содержать текст.</string>
  <string name="MSG_CMD_NAME_TOO_LONG">:warning: Название вашей команды слишком большое (макс. {}, у вас {})</string>
  <string name="MSG_CMD_RESPONSE_TOO_LONG">:warning: Ответ вашей команды слишком большой (макс. {}, у вас {})</string>
  <string name="MSG_CMD_ALREADY_EXISTS">Эта команда уже существует! Вы хотите записать эту команду вместо текущей? Напишите \'{}\' что-бы подтвердить.</string>
  <string name="MSG_CMD_ADDED">Команда \'{}\" добавлена.</string>
  <string name="MSG_CMD_SEPARATE">:no_entry_sign: Неверные аргументы, разделите команду и ответ с помощью |</string>
  <string name="MSG_CMD_TIMEOUT">Подтверждение не получено, не перезаписываю текущую команду. :upside_down:</string>
  <string name="MSG_CMD_NO_SUCH_COMMAND">:warning: Не удалось убрать команду (коианда не существует)</string>
  <string name="MSG_CMD_NO_CUSTOM">Собственных команд не существует на этом сервере. Добавьте их с помощью `{}cmd add trigger|response`!</string>
  <string name="MSG_CMD_LIST">Собственные команды: (страница **{}**/{})
```{}```</string>
  <string name="MSG_CMD_LIST_NO_PAGE">:eyes: Такой страницы не существует! Есть только **{}** страниц с собственными командами.</string>
  <string name="MSG_CMD_REMOVE_FAIL">:warning: Не удалось убрать команду (не существует)</string>
  <string name="MSG_CMD_REMOVE_PARAMS">:warning: Пожалуйста уточните команду которую вы хотите убрать.</string>
  <string name="MSG_CMD_LIST_TOO_LONG">Ваши команды слишком большие что-бы их роказать. Пожалуйста рассмотрите удаление нескольких команд. Если вы не помните название команд, свяжитесь с владельцем бота.</string>
  <string name="MSG_CMD_STATUS">:information_source: У вас **{}** / {} собственных команд</string>
  <string name="MSG_LANG_LIST">Доступные языки:
{}

Пожалуйста помните что эта функция ещё не идеальна и некоторые переводы могут отсутствовать. Также сообщения !help **не** переведены.</string>
  <string name="MSG_LANG_NOT_AVAILABLE">:eyes: Этот язык не поддерживается. :cry:</string>
  <string name="MSG_LANG_SET">Установленный язык **{}**. {}</string>
  <string name="MSG_LANG_TRANS">(Переводчики: {})</string>
  <string name="MSG_LANG_CURRENT">На данный момент вы используете `{}` ({}), но вы ннаверное уже это знаете :stuck_out_tongue: Напишите `{}language list` что-бы посмотреть все языки.</string>
  <string name="MSG_SETTINGS_WRONG_USAGE">:warning: Неправильное использование, напишите `help nano.settings`.
:crystal_ball: Если вы хотите увидеть текущие настройки, напишите `nano.displaysettings`.</string>
  <string name="MSG_SETTINGS_NOT_TEXT">Канал для записи не может быть голосовым! Хорошая попытка :smile:</string>
  <string name="MSG_SETTINGS_LOGCHANNEL_SET">Канал для записи теперь **{}** :smile:</string>
  <string name="MSG_SETTINGS_LOGCHANNEL_DISABLED">Канал для записи **отключён** :ok_hand:</string>
  <string name="MSG_SELFROLE_ADMIN_REMOVED">:ok: **{}** убран со списка общих ролей.</string>
  <string name="MSG_SELFROLE_ADMIN_ADDED">:ok: Общая роль создана.</string>
  <string name="MSG_SELFROLE_ALR_EX">:warning: Эта общая роль уже существует!</string>
  <string name="MSG_SELFROLE_INACCESSIBLE">:warning: **{}** не доступно (возможно выше чем самая высокая роль Nano или у Nano  не хватает прав что-бы управлять ролями)</string>
  <string name="MSG_SELFROLE_REMOVE_NOT_PRESENT">:warning: Не общая роль.</string>
  <string name="MSG_SELFROLE_NOT_ANYMORE">:warning: Не роль на этом сервере.</string>
  <string name="MSG_SELFROLE_LIST">**Общие роли** (страница **{}**/{})

{}</string>
  <string name="MSG_SELFROLE_NOT_PRESENT">:warning: Не могу добавить роль: **{}** не существует на этом сервере</string>
  <string name="MSG_SELFROLE_REMOVED">:ok_hand: Убрал **{}** из вашего списка ролей.</string>
  <string name="MSG_SELFROLE_ADDED">:ok_hand: Роль создана.</string>
  <string name="MSG_SELFROLE_NONE">На данный момент общих ролей не существует. Добвьте общую роль с помощью команды `nano.settings selfrole add [role]` !</string>
  <string name="MSG_SELFROLE_NO_PAGE">:eyes: Страницы не существует! На данный момент только **{}** страниц.</string>
  <string name="MSG_SELFROLE_TOO_MANY">:warning: Количество общих ролей достигло максимума! У вас может быть только **{}** общих ролей одновременно.</string>
  <string name="MSG_SETTINGS_WF_OPTIONS">фильтр слов | словофильтр | фильтрировать слова | фильтрироватьслова</string>
  <string name="MSG_SETTINGS_SF_OPTIONS">фильтр спама | спамофильтр | фильтровать спам | фильтрспам</string>
  <string name="MSG_SETTINGS_IF_OPTIONS">инвайтофильтр | фиьтровапть инвайты | фильтринвайт</string>
  <string name="MSG_SETTINGS_DEFCHAN_SET">:ok: Новый исходный канал **{}**.</string>
  <string name="MSG_SETTINGS_DEFCHAN_RESET">:ok: Новый исходный канал изначальный - **{}**.</string>
  <string name="MSG_SETTINGS_WORD">Фильтр слов {}</string>
  <string name="MSG_SETTINGS_SPAM">Фильтр спама {}</string>
  <string name="MSG_SETTINGS_INVITE">Фильтр инвайтов {}</string>
  <string name="MSG_SETTINGS_NOT_A_SETTING">**{}** не настройка. Настройки: logchannel, selfrole, invitefilter, wordfilter, spamfilter, defaultchannel.</string>
  <string name="MSG_SETTINGS_NO_BLACKLIST">Чёрных списков не существует</string>
  <string name="MSG_SETTINGS_DISPLAY">**Настройки сервера**
```markdown
## Приставка
{}

## Игнорируемые каналы
{}

====================

## Фильтр спама
{}

## Фильтр слов
{}

## Фильтр инвайтов
{}

====================

## Канал для записи
{}

## Изначальный канал
{}

===================
```</string>
  <string name="MSG_SETTINGS_DISPLAY_2">**Сообщения**
```markdown

[1.]: Присоединение
{}

[2.]: Уход
{}

[3.]: Кик
{}

[4.]: Бан
{}
```</string>
  <string name="MSG_BLACKLIST_ADDED">Успешно добавил &lt;#{}&gt; в игнорируемые каналы :ok_hand:</string>
  <string name="MSG_BLACKLIST_REMOVED">Игнорирование канала &lt;#{}&gt; отменено :ok_hand:</string>
  <string name="MSG_BLACKLIST_REMOVE_FAIL">Игнорирование канало не могло быть отменено потому-что такого канала нет.</string>
  <string name="MSG_BLACKLIST_DOESNT_EXIST">&lt;#{}&gt; не явлется игнорируемым каналом.</string>
  <string name="MSG_BLACKLIST_TOO_MANY">Слишком много игнорируемых каналов! **{}** является максимальным количеством игнорируемых каналов.</string>
  <string name="MSG_BLACKLIST_LIST">Игнорируемые каналы:

{}</string>
  <string name="MSG_BLACKLIST_NONE">Игнорируемые каналы отсутствуют на этом сервере. :smile:</string>
  <string name="MSG_RESET_CONFIRM">:warning: Вы уверены что хотите сбросить настройки Nano к заводским? (Это не включает обеззвучение пользователей, общие роли и команды)
Подтердите нажав на \'{}\'.</string>
  <string name="MSG_RESET_CONFIRM_TIMEOUT">Подтверждение НЕ получено, НЕ сбрасываю настройки :upside_down:</string>
  <string name="MSG_RESET_DONE">Сброшено. :white_check_mark:</string>
  <string name="MSG_PREFIX_CHANGED">Приставка изменена на **{}** :ok_hand:</string>
  <string name="MSG_PREFIX_PLS_ARGUMENTS">У этой команды должен быть аргумент: приставка которую вы хотите установить.</string>
  <string name="MSG_SETUP_TIMEOUT">У вас вышло время :upside_down: (перерыв длится {} секунд)</string>
  <string name="MSG_SETUP_WELCOME">{} добро пжаловать в **НАСТРОЙКУ СЕРВЕРА**!
Эта настройка познакомит вас с основеыми настройками что-бы помочь вам быстро всё настроить. Вы сможите установить вещи как приставку, фильтры спама и матных слов и другие настройки.

Ну что, начнём? 

:notepad_spiral: Записка: *Вы начали настройку и только ваши ответы будут приниматься, так-что не волнуйтесь по поводу того что другие смогут отвечать на мои вопросы.*</string>
  <string name="MSG_SETUP_RESET">Вы хотите сбросить все настройки связанные с ботами на этом сервере?
(это включает в себя все стандартные настройки включая игнорируемые каналы, канал для записи, префикс и сообщения при входе, бане и кике).

```md
[{yes}](Сбрасывает все настройки)
[{no}](Оставляет все настройки)```</string>
  <string name="MSG_SETUP_PREFIX_TEXT">Приставка</string>
  <string name="MSG_SETUP_PREFIX">Какую присиавку хотели бы вы использовать для всех команд?
Пример: имея *!* как вашу приставку, команды будут выглядеть так: `!help` `!ping` и т.д.

```md
[{prefix}](Префикс который вы хотите)```</string>
  <string name="MSG_SETUP_JOINMSG_TEXT">Текст</string>
  <string name="MSG_SETUP_JOINMSG">Что бы вы хотели что-бы я говорил когда человек присоединяется к вашему серверу?

Следующее форматирование прилагается:
*:user* -&gt; упоминание пользователя
*:username* -&gt; имя пользователя
*:server* -&gt; имя сервера

```md
[{text}](Текст который вы хотите видеть)
[{none}](Отключает сообщения при входе)```</string>
  <string name="MSG_SETUP_SPAM">Вы хотите что-бы я фильтровал спам?
```md
[{yes}](Включает фильтр)
[{no}](отключает фильтр)```</string>
  <string name="MSG_SETUP_SWEARING">Вы хотите что-бы я фильтровал мат?
```md
[{yes}](Включает фильтр)
[{no}](Отключает фильтр)```</string>
  <string name="MSG_SETUP_INVITES">Вы хотите что-бы я фильтровал ссылки для приглашения?
```md
[{yes}](Включает фильтр)
[{no}](Выключает фильтр)```</string>
  <string name="MSG_SETUP_LOGCHANNEL_MENTION">#упоминание канала</string>
  <string name="MSG_SETUP_LOGCHANNEL">Какой канал хотели бы вы использовать для записывания моего прогресса?
```md
[{mention}](Использует этот канал)
[{none}](Отключает записывание)```</string>
  <string name="MSG_SETUP_LOGCHANNEL_DISABLED">Записывание отключено.</string>
  <string name="MSG_SETUP_LOGCHANNEL_SET">Канал для записывания установлен на **{}**</string>
  <string name="MSG_SETUP_LOGCHANNEL_INVALID">:x: Недопустимый ответ / канал для записывания.</string>
  <string name="MSG_SETUP_COMPLETE">**Это заключает основную настройку сервера.**
Есть больше настроек если они вам нужны:

➤игнорирование канала - `nano.blacklist add/remove #канал`
➤сообщение при уходе с сервера - `_leavemsg сообщение`
➤сообщение при бане - `_banmsg сообщение`
Это не все настройки. Увеличенный список находится снизу.

Команды администратора и модератора могут быть использованы людьми с ролью **\"Nano Admin/Mod\"**.
Если вы *запутались и не знаете как продолжать* попробуйте зайти на наш **FAQ** на &lt;https://nanobot.pw/faq.html&gt;
или присоединитесь к нашему **серверу поддержки** на &lt;https://discord.nanobot.pw&gt;

Вы и все админы могут создавать и удалять собственные командыс помощью `_cmd add/remove/list команда|ответ`.
Для полного списка команд и их объяснений, зайдите на &lt;http://nanobot.pw/commands.html#admin&gt;</string>
  <string name="MSG_PERMISSION_NOARG">:warning: Отсутствующие аргументы, пожалуйста попробуйте команду help.</string>
  <string name="MSG_PERMISSION_WRONGARG">:warning: Недопустимая субкоманда, попробуйте `_permission help`</string>
  <string name="MSG_PERMISSION_CREATION_REASON">Была выполнена команда для разрешений, создаю роль с разрешениями.</string>
  <string name="MSG_PERMISSION_ASSIGN_REASON">Была выполнена команда для разрешений, назначаю эту роль.</string>
  <string name="MSG_PERMISSION_ADMIN_CONFIRM">:eyes: Вы уверены что вы хотите дать **{}** разрешения админа? Подтвердите нажав на {}</string>
  <string name="MSG_PERMISSION_MOD_CONFIRM">:eyes: Вы уверены что вы хотите дать **{}** разрешения модератора? Подтвердите нажав на {}</string>
  <string name="MSG_PERMISSION_MISSINGPERM_M">:warning: У вас нету прав что-бы назначать разрешение модератора (вы должны быть админом или владельцем)</string>
  <string name="MSG_PERMISSION_MISSINGPERM_A">:warning: У вас недостаточно прав что-бы назначить роль админа (вы должны быть владельцем)</string>
  <string name="MSG_PERMISSION_TIMEOUT">:eyes: Время истекло во время ожидания ответа.</string>
  <string name="MSG_PERMISSION_ADMIN_A">:ok_hand: **{}** имеет права администратора</string>
  <string name="MSG_PERMISSION_ADMIN_R">:ok_hand: Права администратора отобраны у **{}**</string>
  <string name="MSG_PERMISSION_MOD_A">:ok_hand: **{}** имеет права модератора</string>
  <string name="MSG_PERMISSION_MOD_R">:ok_hand: Права модератора отобраны у **{}**</string>
  <string name="MSG_PERMISSION_HELP">**Команда _permission позволяет вам быстро назначать/убирать админов и модов.**
Что-бы дать разрешения администратора, используйте команду _permission admin @упоминание (если этот пользователь уже админ, разрешения удалятся)
Что-бы дать разрешение модератора, используйте _permissions mod @упоминание (тоже самое здесь)</string>
  <string name="MSG_PING_MEASURING">:ping_pong: Измеряю...</string>
  <string name="MSG_PING_RESULT">:ping_pong: **Pong!** (лаг: {} мс, реакция: {} мс)</string>
  <string name="MSG_LOGPOST_SAY">{}say выполнено</string>
  <string name="MSG_LOGPOST_NUKE">{}nuke выполнено</string>
  <string name="MSG_LOGPOST_SELFROLE">{}selfrole выполнено</string>
  <string name="MSG_LOGPOST_SELFROLE_INFO">Пользователь присвоил общественную роль: **{}**</string>
  <string name="MSG_LOGPOST_SELFROLE_INFO2">Пользователь удалил свою роль: **{}**</string>
  <string name="MSG_UPTIME">Я без остановки отвечал людям уже **{} дней, {} часов, {}минут, и {} секунд!** :open_mouth:</string>
  <string name="MSG_ROLL">{}, вы выбросили {}</string>
  <string name="MSG_DICE">:game_die: {} на кубиках... **{}**</string>
  <string name="MSG_DICE_TOO_MANY">:eyes: Слишком много кубиков (макс. {})</string>
  <string name="MSG_DICE_TOO_BIG">:eyes: Выражение на кубиках слишком большое! (максимум сторон и кубиков: {})</string>
  <string name="MSG_DICE_RESULTS">:game_die: **{}**, вы кинули:

```markdown
{}

==============

[1.]:Итого
{}баллов
```</string>
  <string name="MSG_DICE_ENTRY">## {}
{} балл(ов)</string>
  <string name="MSG_DICE_INVALID">Неверное выражение, попробуйте `_help dice`</string>
  <string name="MSG_DECIDE_NORMAL">**барабанная дробь**... Я принял решение: {}</string>
  <string name="MSG_DECIDE_SPECIAL">Угадайте что? {}. **бадум тсс.**</string>
  <string name="MSG_DECIDE_NO_ARGS">:grey_exclamation: Вы должны предоставить хотя-бы два варианта.</string>
  <string name="MSG_8BALL">:8ball: {}</string>
  <string name="MSG_8BALL_STRINGS">Это точно | Это безусловно так | Без сомнения | Вы можете положиться на это | Скорее всего | Да | Спросите позже | Не могу предсказать сейчас| Сконцентрируйтесь и спросите снова | Я хотел бы сказать да | ПРОСТО СДЕЛАЙ ЭТО | Мой ответ является нет | Мои источники говорят, что нет | Признаки указывают на да</string>
  <string name="MSG_AVATAR_OWNERSHIP">Аватар **{}**: {}</string>
  <string name="MSG_AVATAR_NONE">У **{}** нет аватара. :expressionless:</string>
  <string name="MSG_SAY_NOPERM">Не иогу отправлять сообщения **&lt;#{}&gt;**: отсутствуют разрешения!</string>
  <string name="MSG_AYYLMAO">Мое вдохновение в мире мемов.</string>
  <string name="MSG_WHOKNOWS">¯\_(ツ)_/¯</string>
  <string name="MSG_GIPHY_TOOFAST">:shield: Эй, слишком быстро! Nano достиг лимита скорости для гифов (просто подождите немного и попробуйте заново).</string>
  <string name="MSG_GIPHY_NOSUCHTAG">Гифа с тэгом {} не существует, отсылаю случайный гиф</string>
  <string name="MSG_GIPHY_POWEREDBY">На платформе Giphy</string>
  <string name="MSG_MEME_USAGE">Неправильное использование. Попробуйте _help caption/_help meme для информации.</string>
  <string name="MSG_MEME_NONEXISTENT">Этот мем не существует. покойся с миром (тссс, смотрите топовые мемы здесь https://imgflip.com/memetemplates )</string>
  <string name="MSG_MEME_FOOTER">Работает с помощью imgflip.com</string>
  <string name="MSG_RIP">Покойся в пепперони{}.
`{}` *молитв пропето*...</string>
  <string name="MSG_ACHIEVMENT_NOTEXT">Пожалуйста, укажите текст который вы хотите иметь на изображении.</string>
  <string name="MSG_HELP">**Здравствуйте, меня зовут Nano!**

Что-бы познакомиться с простыми командами, напишите `_help simple`
Если вы хотите подробную информацию о команде, напишите `_help [название команды]`.

Также вы можете прочитать вики страницу:
http://nanobot.pw/commands.html
Если вы админ/владелец, напишите `_setup`.
Очень рекомендовано присоединиться к \"официальному\" серверу Nano для объявлений и поддержки: https://discord.gg/FZJB6UJ

Используя Nano вы соглашаетесь что мы храним часть информации пользователя как имена пользователей, серверов и каналов для лучшей работы. что-бы узнать подробнее, напишите `_tos`.</string>
  <string name="MSG_TOS">:shield: ** Условия Использования**

20 августа, 2017 года, Дискорд обновил свои Условия Использования. Владельцы ботов должны говорить пользователям какую информацию хранят боты, как **имена пользователей, серверов и каналов**.

Что-бы узнать подробнее, прочитайте &lt;http://nanobot.pw/tos.html&gt;</string>
  <string name="MSG_HELP_SIMPLE">`_hello` - Приветствует вас или упомянутого человека.
`_randomgif` - Присылает случайное гиф из Giphy
`_roll number` - показывает случайное число
`_wiki term` - даёт описание термина из Википедии
`_urban term` - даёт описание термина из Urban Dictionary
`_decide option|option...` - решает между вариантами что-бы вам не приходилось
`_tf item-name` - цены предметов из backpack.tf
`_steam user-id` - поиск пользователей в Steam

Это только часть простых команд. Для более подробной информации по каждой команде, напишите `_help команда` или `_cmds` что-бы посмотреть вики страницу со всеми командами.</string>
  <string name="MSG_HELP_CMDWEB">Команды и их объяснения на этом сайте:
http://nanobot.pw/commands.html</string>
  <string name="MSG_HELP_CMD_SPEC">Прочитайте больше про эти команды здесь: {}</string>
  <string name="MSG_HELP_CMDNOTFOUND">Команда не найдена.
**(Используйте `_help [command]`)**</string>
  <string name="MSG_HELP_DESC">Описание</string>
  <string name="MSG_HELP_USE">Использование</string>
  <string name="MSG_HELP_ALIASES">Псевдонимы</string>
  <string name="MSG_BUG">Нашли баг? Сообщите мне, (**DefualtSimon**) на Дискорде
Вы можете найти меня здесь: https://discord.gg/FZJB6UJ</string>
  <string name="MSG_REPORT_EMPTY">Вы не можете отослать пустой отчёт.</string>
  <string name="MSG_REPORT_RATELIMIT">На вас наложены ограничения по скорости. Попробуйте через 5 минут.</string>
  <string name="MSG_REPORT_THANKS">**Спасибо** за ваше предложение.</string>
  <string name="MSG_REPORT_EE_THX">Привеееет :wave:</string>
  <string name="MSG_IMDB_ERROR">Что-то пошло не так при попытке получить информацию о фильме.</string>
  <string name="MSG_IMDB_ERROR2">Что-то пошло не так... Попробуйте ещё раз?</string>
  <string name="MSG_IMDB_INVALID_USAGE">Неверное использование команду, используйте `{}help imbd`</string>
  <string name="MSG_IMDB_NEED_TITLE">:warning: Нужно вписать название.</string>
  <string name="MSG_IMDB_ERROR_REPDEV">Что-то пошло не так, пожалуйста сообщите об этом разработчикм, предпочтительно со скриншотом. Спасибо!</string>
  <string name="MSG_IMDB_NORESULTS">:eyes: Нет результатов.</string>
  <string name="MSG_IMDB_CANTPERSON">Вы не можете дать сюжет человека :rofl:</string>
  <string name="MSG_IMDB_PLOT">История о **{}**
```{}```</string>
  <string name="MSG_IMDB_SERIES">сериал</string>
  <string name="MSG_IMDB_PLOT_MISSING">У этого фильма/сериала отсутствует описание сюжета.</string>
  <string name="MSG_IMDB_GENRES">Жанры: {}</string>
  <string name="MSG_IMDB_AVGRATING">Средняя оценка: ** {} / 10 **</string>
  <string name="MSG_IMDB_SEASONS">Сезоны: ** {} **</string>
  <string name="MSG_IMDB_SUMMARY">
Обобщение: 
```{}```
</string>
  <string name="MSG_IMDB_POSTER">Постер: {}</string>
  <string name="MSG_IMDB_PERSON_NOT_SUPPORTED">Поиск пользователя ещё не работает.</string>
  <string name="MSG_IMDB_TRAILER">**{}**\'s трейлеров на IMDb:

{}</string>
  <string name="MSG_IMDB_TRAILER_MISSING">У этого фильма/сериала нету трейлера на IMDb.</string>
  <string name="MSG_IMDB_RATINGS">Рейтинги **{}**

Рейтинги пользователей на TMDb:__**{}** из 10_</string>
  <string name="MSG_IMDB_RATINGS_MISSING">Похоже у это фильма/сериала нет рейтинга. Странно.</string>
  <string name="MSG_IMDB_HELP">**помощь по TMDb/IMDb**

`_imdb search [название]`, `_imdb plot [title]`, `_imdb trailer [title]`, `_imdb rating [title]`</string>
  <string name="MSG_CAT_FAILED">Я не мог получить случайное фото кота... :cry:</string>
  <string name="MSG_CAT_FOOTER">Работает с помощью thecatapi.com</string>
  <string name="MSG_XKCD_FAILED">Не мог прислать xkcd :cry:</string>
  <string name="MSG_XKCD">Комикс XKCB номер {}:</string>
  <string name="MSG_XKCD_SOURCe">Источник: {}</string>
  <string name="MSG_XKCD_NO_SUCH">Этого номера XKCB не существует.</string>
  <string name="MSG_MC_HELP">**Майнкрафт**
```css
_mc name/id:meta - искать предметы и смотреть их информацию```</string>
  <string name="MSG_MC_NO_ITEMS">**Предмета с этим названием/id не существует**</string>
  <string name="MSG_MC_PLSARUGMENTS">Пожалуйста уточните название/id предмета.</string>
  <string name="MSG_MC_DETAILS">**{}**```css
Id: {}:{}```</string>
  <string name="MSG_MOD_MSG_DELETED">Сообщение удалено - {}</string>
  <string name="MSG_MOD_SPAM_G">спам (неразборчивость сообщений)</string>
  <string name="MSG_MOD_SPAM_C">спам (капс лок)</string>
  <string name="MSG_MOD_SPAM_R">спам (повторяющиеся сообщения)</string>
  <string name="MSG_MOD_SPAM_M">спам (спам упоминаниями)</string>
  <string name="MSG_MOD_SWEARING">ругань</string>
  <string name="MSG_MOD_INVITE">ссылка для приглашения</string>
  <string name="MSG_OSU_ERROR">Что-то пошло не так... :thinking:</string>
  <string name="MSG_OSU_MISSING_PARAM">Отсутствует</string>
  <string name="MSG_OSU_NOT_ENOUGH_PLAYS">:expressionless: У пользователя не достаточно данных что-бы вывести на дисплей.</string>
  <string name="MSG_OSU_NO_NAME">Пожалуйста укажите имя пользователя которое вы будете искать.</string>
  <string name="MSG_OSU_TITLE">{} (уровень {})</string>
  <string name="MSG_OSU_DESC">**Ранг**:
    **Мир**:            #{}
    **Страна** (**{}**):  #{}

PP: **{}** (прослушано {} композиций)</string>
  <string name="MSG_OSU_TOTAL_SC">Общие баллы</string>
  <string name="MSG_OSU_RANKED_SC">Баллы в рангах</string>
  <string name="MSG_OSU_AVG_ACC">Средняя точность</string>
  <string name="MSG_OSU_TIME">Поиск занял {} мс</string>
  <string name="MSG_RATELIMIT">{} Эй, остынь! :snowflake: Ты слишком быстро всё делаешь, попробуй через несколько секунд.</string>
  <string name="MSG_NANO_SLEEP">Спокойной ночи! :sleeping:</string>
  <string name="MSG_NANO_WAKE">:wave:</string>
  <string name="MSG_NANO_WASNT_SLEEPING">Не был в режиме сна.</string>
  <string name="MSG_REMINDER_PRIVATE">:alarm_clock: Вы просили напомнить вам:
```{}```</string>
  <string name="MSG_REMINDER_CHANNEL">:alarm_clock: Таймер закончился!
```{}```</string>
  <string name="MSG_REMINDER_HELP">**Помощь по оповещениям**

`_remind me in [время]: [сообщение]` - оповещает вас в ЛС
`_remind here in [время]: [сообщение]` - оповещает всех в этом канале</string>
  <string name="MSG_REMINDER_WU_ME">Неправильное использование команды. Попробуйте `{}help remind me in`</string>
  <string name="MSG_REMINDER_WU_HERE">Неправильное использование команды. Попробуйте `{}help remind here in`</string>
  <string name="MSG_REMINDER_NO_BRACKETS">Не используйте **[** и **]** ! Попробуйте ещё раз без них.</string>
  <string name="MSG_REMINDER_INVALID_RANGE">Недопустимый временной интервал (от **{}** секунд до **{}** дней)</string>
  <string name="MSG_REMINDER_TO_LITERAL">к</string>
  <string name="MSG_REMINDER_SET">Напоминание установлено :smile:</string>
  <string name="MSG_REMINDER_NO_PARTIALS">Пожалуйста не используйте неполные минуты/часы/дни и т.д... (например 1.7 дней) - используйте `1d 16h 48min` вместо этого :wink:</string>
  <string name="MSG_REMINDER_SOON">скоро™</string>
  <string name="MSG_REMINDER_TIME_LEFT">через **{}**</string>
  <string name="MSG_REMINDER_LIST_NONE">У вас нет напоминаний.</string>
  <string name="MSG_REMINDER_TOO_LONG_CONTENT">Содержание вашего напоминания слишком длинное! (максимум {})</string>
  <string name="MSG_REMINDER_LIST">Ваши напоминания:
 ```md
{}```</string>
  <string name="MSG_REMINDER_DELETE_ALL">Все напоминания были удалены.</string>
  <string name="MSG_REMINDER_DELETE_NONE">Напоминания с таким содержанием не существует.</string>
  <string name="MSG_REMINDER_DELETE_SUCCESS">Напоминание удалено.</string>
  <string name="MSG_REMINDER_LIMIT_EXCEEDED">:warning: Вы превысили максимальное количество напоминаний (**{}** одновременно)</string>
  <string name="MSG_REMINDER_INVALID_FORMAT">:warning: Недопустимый временной формат, пожалуйста используйте sec, min, d, и т.д...</string>
  <string name="MSG_REMINDER_LIST_L">*{}
&gt;{}</string>
  <string name="MSG_STATUS_RATELIMIT">Эту команду очень сложно выполнять так как она требует сильного использования процессора, поэтому она может быть использована только раз в пять минут.
Пожалуйста попробуйте ещё раз.</string>
  <string name="MSG_STATUS_STATS">Статистика</string>
  <string name="MSG_STATUS_SERVERS">Сервера</string>
  <string name="MSG_STATUS_SERVERS_L">{} серверов</string>
  <string name="MSG_STATUS_USERS">Пользователи</string>
  <string name="MSG_STATUS_USERS_L">{} пользователей</string>
  <string name="MSG_STATUS_CHANNELS">Каналы</string>
  <string name="MSG_STATUS_CHANNELS_L">{} каналов</string>
  <string name="MSG_DEBUG_VERSION">Версия Nano</string>
  <string name="MSG_DEBUG_DPY">discord.py</string>
  <string name="MSG_DEBUG_RAM">Использование оперативной памяти</string>
  <string name="MSG_DEBUG_GC">{} МБ (Сборщик мусора собрал {} MB)</string>
  <string name="MSG_DEBUG_CPU">Использование процессора</string>
  <string name="MSG_DEBUG_CPU_L">{} %</string>
  <string name="MSG_DEBUG_REMINDERS">Текущие напоминания</string>
  <string name="MSG_DEBUG_VOTES">Текущие опросы</string>
  <string name="MSG_DEBUG_R_MEM">Память Redis</string>
  <string name="MSG_DEBUG_R_KEYS">Ключи Redis</string>
  <string name="MSG_DEBUG_UPTIME">Время работы</string>
  <string name="MSG_DEBUG_UPTIME_L">{} днейб {}:{}:{}</string>
  <string name="MSG_DEBUG_INFO">**Вещи для очистки:**</string>
  <string name="MSG_DEBUG_MULTI">```md
[1.] Версии

## Nano
{}

## dicord.py
{}

[2.]: Ресурсы

## Использование оперативной памяти
{} (Сьорщик мусора собрал {} MB)

## Использование процессора
{}

[3.] Cостояние

## Текущие напоминания
{}

## Текущие опросы
{}

[4.] Redis

## Память
{}

## Ключи
{}```
</string>
  <string name="MSG_DEBUG_MULTI_2">**Информация о осколках**

:diamond_shape_with_a_dot_inside: Осколков: **{}**
:map: Id осколка этого случая: **{}**</string>
  <string name="MSG_STATS_MSGS">Сообщения отправлены</string>
  <string name="MSG_STATS_ARGS">Неверные значения получены</string>
  <string name="MSG_STATS_PERM">Злоупотребление командами испробовано</string>
  <string name="MSG_STATS_HELP">Людям оказана помощь</string>
  <string name="MSG_STATS_IMG">Изображения отправлено</string>
  <string name="MSG_STATS_VOTES">Голосов получено</string>
  <string name="MSG_STATS_SLEPT">Количество раз уходил в сон</string>
  <string name="MSG_STATS_PONG">Количество раз сделал Pong!</string>
  <string name="MSG_STATS_INFO">**Статистика**</string>
  <string name="MSG_ADVS_TITLE">:hammer: Продвинутые настройки v{}</string>
  <string name="MSG_ADVS_DESC">Количество уникальных пользователей: **{}**
Количество уникальных гильдий: **{}**
*(Только количество использованных команд считается)*</string>
  <string name="MSG_ADVS_HISTORY">**Использование в последний день/неделю/месяц**</string>
  <string name="MSG_ADVS_HISTORY_BODY">```md
*Сегодня
[{day_u} пользователей]({day_g} уникальных гильдий)

*Эта неделя
[{week_u} пользователей]({week_g} уникальных гильдий)

*Этот месяц
[{month_u} пользователей]({month_g} уникальных гильдий)
```</string>
  <string name="MSG_PREFIX_OHYEAH">Вы угадали!</string>
  <string name="MSG_PREFIX">Приставка этого сервера **{}**</string>
  <string name="MSG_MEMBERS_LIST">*__Пользователи__*:

{}
</string>
  <string name="MSG_MEMBERS_TOTAL">Всего: **{}** пользователей</string>
  <string name="MSG_MEMBERS_AMOUNT">В этой гильдии всего **{}** пользователей</string>
  <string name="MSG_SERVER_VL">Уровень верификации</string>
  <string name="MSG_SERVER_VL_NONE">Отсутствует</string>
  <string name="MSG_SERVER_VL_LOW">Низкий</string>
  <string name="MSG_SERVER_VL_MEDIUM">Средний</string>
  <string name="MSG_SERVER_VL_HIGH">Высокий (╯°□°）╯︵ ┻━┻</string>
  <string name="MSG_SERVER_ID">ID: *{}*</string>
  <string name="MSG_SERVER_DATE_CREATED">Сервер создан {}</string>
  <string name="MSG_SERVER_MEMBERS">Пользователи [{} всего]</string>
  <string name="MSG_SERVER_MEMBERS_L">{} онлайн</string>
  <string name="MSG_SERVER_CHANNELS">Каналы [{} всего]</string>
  <string name="MSG_SERVER_CHANNELS_L">{} голосовых | {} текстовых</string>
  <string name="MSG_SERVER_ROLES">Роли</string>
  <string name="MSG_SERVER_ROLES_L">{} своих</string>
  <string name="MSG_SERVER_OWNER">Владелец сервера</string>
  <string name="MSG_SERVER_OWNER_L">{}#{} ID:{}</string>
  <string name="MSG_SERVER_INFO">:book: **Информация сервера:**</string>
  <string name="MSG_STEAM_INVALID_URL">Пожалуйста впишите **окончание** (\"vanity\") URL-адреса, а не *весь* адрес!</string>
  <string name="MSG_STEAM_INVALID_PARAMS">Неверное использование команду, используйте `{}help steam`</string>
  <string name="MSG_STEAM_NEED_URL">Пожалуйста, укажите url/имя.</string>
  <string name="MSG_STEAM_PRIVATE">Что-то пошло не так. У пользователя возможно личный профиль.</string>
  <string name="MSG_STEAM_PRIVATE_FRIENDS">Найти друзей не удалось (Возможно у пользователя личный профиль)</string>
  <string name="MSG_STEAM_PRIVATE_GAMES">Найти игры не удалось (Возможно у пользователя личный профиль)</string>
  <string name="MSG_STEAM_FRIENDS">:video_game: **{}**

*Друзья:* {}</string>
  <string name="MSG_STEAM_GAMES">:video_game: **{}**

*Купленные игры:* {}</string>
  <string name="MSG_STEAM_GAMES_TOO_MANY">Это сообщение не помещается в Дискорд: **у пользователя слишком много игр что-бы отобразить (лол)**</string>
  <string name="MSG_STEAM_FRIENDS_TOO_MANY">Это сообщение не помещается в Дискорд: **у пользователя слишком много друзей что-бы отобразить (лол)**</string>
  <string name="MSG_STEAM_USER_INFO">:video_game: **{}**
`css
Статус: {}
Уровень: {}
Игры: {} куплено (включая бесплатные игры)
Друзья: {}```
Ссылка: http://steamcommunity.com/id/{}/</string>
  <string name="MSG_STEAM_ONLINE">Онлайн</string>
  <string name="MSG_STEAM_OFFLINE">Оффлайн</string>
  <string name="MSG_STEAM_HELP">**Команды Steam:**
`!steam user ссылка_сообщества`, `!steam game ссылка_сообщества`</string>
  <string name="MSG_TF_UNAVAILABLE">Эта команда временно недоступна. Приносим извинения.</string>
  <string name="MSG_TF_NO_PARAMS">:warning: Пожалуйста уточните предмет для поиска.</string>
  <string name="MSG_TF_NO_SUCH_ITEM">**Не найден** предмет с таким именем.</string>
  <string name="MSG_TF_LIST">:scales: **{}** *(на bp.tf)*

{}</string>
  <string name="MSG_VOTING_NO_PROGRESS">:warning: Текущего опроса нет...</string>
  <string name="MSG_VOTING_IN_PROGRESS">:warning: Опрос уже действует...</string>
  <string name="MSG_VOTING_I_USAGE">Неверное использование. Попробуйте `{}help poll start1 что-бы узнать подробнее.</string>
  <string name="MSG_VOTING_NO_TITLE">Введите название.</string>
  <string name="MSG_VOTING_NEED_OPTIONS">:warning: Пожалуйста включите хотя-бы два варианта в вашем опросе.</string>
  <string name="MSG_VOTING_EMPTY_ITEM">:x: один или более вариантов вашего опроса пусты!</string>
  <string name="MSG_VOTING_STARTED">:scroll: Опрос начат:

**{}**
```ini
# Варианты

{}```</string>
  <string name="MSG_VOTING_AMOUNT">В целом проголосовало {} человек</string>
  <string name="MSG_VOTING_AMOUNT2">{} голосов</string>
  <string name="MSG_VOTING_END_CONFIRMATION">Вы уверены что хотите закрыть опрос? Нажмите {} для подтверждения.</string>
  <string name="MSG_VOTING_END_ABORT">Время ожидание вышло, опрос не закрывается.</string>
  <string name="MSG_VOTING_ENDED">:dividers: **Голосование окончено:**</string>
  <string name="MSG_VOTING_ERROR">Что-то пошло не так во время окончания голосования.</string>
  <string name="MSG_VOTING_OPTIONS_TM">:warning: Слишком много вариантов (максимум **{}**, вы сделали *{}*)</string>
  <string name="MSG_VOTING_OPTIONS_TL">:warning: Всё слишком большое! (максимальная длина {}, у вас {})</string>
  <string name="MSG_VOTING_S_NONE">Пока никто не проголосовал.</string>
  <string name="MSG_VOTING_S_ONE">Пока проголосовал только один человек.</string>
  <string name="MSG_VOTING_S_MULTI">Пока проголосовало {} человек.</string>
  <string name="MSG_VOTING_STATUS">:bar_chart: Статус опроса:

**{}**
```{}```</string>
  <string name="MSG_VOTING_NOT_NUMBER">Аргумент голосования должен быть учислом.</string>
  <string name="MSG_VOTING_INVALID_NUMBER">Неверный выбор.</string>
  <string name="MSG_VOTING_CHEATER">Читер :smiley: (вы не можете голосовать за несколько вариантов)</string>
  <string name="MSG_VOTING_SOMETHING_WRONG">Что-то пошло не так... :frowning2:</string>
  <string name="MSG_WIKI_QUERY_TOO_LONG">:warning: Поисковый запрос слишком большой (максимум {}, у вас {})</string>
  <string name="MSG_WIKI_DEFINITION">:newspaper: определение:

**{}**
```{}```</string>
  <string name="MSG_WIKI_NO_QUERY">:exclamation: Пожалуйста включите слово которые вы хотите найти.</string>
  <string name="MSG_WIKI_NO_DEF">:open_file_folder: Определение не найдено.</string>
  <string name="MSG_URBAN_DEF_TOO_LONG">Определение слишком большое!</string>
  <string name="MSG_URBAN_NO_QUERY">:exclamation: Пожалуйста включите слово которые вы хотите найти.</string>
  <string name="MSG_URBAN_NO_DEF">:open_file_folder: Определение не найдено.</string>
  <string name="MSG_URBAN_DEFINITION">:space_invader: Определение Urban Dictionary:

**{}**
```{}```</string>
  <string name="MSG_IGDB_NONAME">:mag: Пожалуйста укажите игру которую вы хотите найти.</string>
  <string name="MSG_IGDB_NO_RESULT">:eyes: Нет результатов.</string>
  <string name="MSG_IGDB_GENRES">Жанры</string>
  <string name="MSG_IGDB_PUBLISHERS">Издатели</string>
  <string name="MSG_IGDB_RATING">Рейтинг</string>
  <string name="MSG_IGDB_VIDEO">Трейлер/видео</string>
  <string name="EVENT_JOIN">присоединился</string>
  <string name="EVENT_LEAVE">вышел</string>
  <string name="EVENT_KICK">был кикнут</string>
  <string name="EVENT_SOFTBAN">был за софт-банен</string>
  <string name="EVENT_BAN">был забанен</string>
  <string name="EVENT_SERVER_JOIN">**Привет!** Меня зовут Nano!
Сейчас вы пригласили меня на свой сервер, и вы можете захотеть настроить несколько вещей. Сейчас только владелец сервера может использовать мои запрещённые команды. Но не волнуйтесь, вы можете дать разрешения админа с помощью добавления роли **Nano Admin**!

Что-бы начать базовую настройку, напишите `!setup` если вы владелец сервера. Это поможет вам настроить некоторые простые вещи.
После этого, вы наверное захотите попробовать `!commands` что-бы познакомиться с моими командами.


Также, я рекомендую присоединиться к \"официальному\" серверу Nano для объявлений и помощи: https://discord.gg/FZJB6UJ

Используя Nano вы соглашаетесь что мы храним часть информации пользователя как названия пользователей, серверов и каналов что-бы улучшить работу. Что-бы узнать подробнее напишите `!tos`.</string>
</resources>
