<?xml version="1.0" encoding="utf-8"?>
<!--Generated by crowdin.com-->
<resources>
  <string name="CONV_Q_HOW">kako si</string>
  <string name="CONV_Q_WUP">kaj dogaja</string>
  <string name="CONV_Q_SNOW">greva naredit snežaka</string>
  <string name="CONV_Q_DIE">crkni</string>
  <string name="CONV_Q_AYY">ayy</string>
  <string name="CONV_Q_SLEEP">kdaj nehaš | si kdaj utrujen | sploh spiš | ali spiš</string>
  <string name="CONV_Q_RIP">rip</string>
  <string name="CONV_Q_MASTER">ali imaš gospodarja</string>
  <string name="CONV_Q_WHAT">kaj je to</string>
  <string name="CONV_Q_LOVE">ljubim te</string>
  <string name="CONV_Q_HELLO">ojla | živjo | zdravo</string>
  <string name="CONV_MOOD_LIST">Fajn! | Dobro mi gre. | Super sem. Sporočila letijo z mene kt da sm božiček, punčiiiii! | Do zdaj sem imel krasen dan.</string>
  <string name="CONV_SNOW">Daj, greva se igrat!</string>
  <string name="CONV_NAH">Ne bo šlo :wink:</string>
  <string name="CONV_NOPE">Nope.avi</string>
  <string name="CONV_AYYLMAO">Ayy. Lmao.</string>
  <string name="CONV_RIP">Rest in pepperoni **in se pokloni**</string>
  <string name="CONV_MASTER">Trapets nima gospodarja.</string>
  <string name="CONV_SPARTA">TO JE ŠPARTA!</string>
  <string name="CONV_LOVE">&lt;3</string>
  <string name="CONV_HI">Živjo!</string>
  <string name="PERM_HIERARCHY">:warning: S to vlogo (role) se nimaš kaj zafrkavati (si prenizko na \"lestvici\"). ¯\_(ツ)_/¯</string>
  <string name="PERM_ADMIN">:warning: Nimaš dovoljenja za uporabo tega ukaza (moraš biti admin).</string>
  <string name="PERM_MOD">:warning: Nimaš dovoljenja za uporabo tega ukaza (moraš biti moderator/ka).</string>
  <string name="PERM_OWNER">:warning: Nimaš dovoljenja za uporabo te funkcije. (samo za lastnika bota)</string>
  <string name="INFO_PREFIX">Predpona za ta server je **{}**</string>
  <string name="INFO_DONE">Opravljeno</string>
  <string name="INFO_OK">V redu</string>
  <string name="INFO_ON">Omogočeno</string>
  <string name="INFO_YES">Ja</string>
  <string name="INFO_NO">Ne</string>
  <string name="INFO_HELLO">Živjo!</string>
  <string name="INFO_OFF">Onemogočeno</string>
  <string name="INFO_HI">Živjo, {}</string>
  <string name="INFO_USE">Uporabi</string>
  <string name="INFO_ALIASES">Psevdonim</string>
  <string name="INFO_DESCRIPTION">Opis</string>
  <string name="INFO_DISABLED">Izklopljeno</string>
  <string name="INFO_GENERAL">**Živjo! Jaz sem Nano!**
Imam svoj GitHub repozitorij! `!github`
Moja trenutna verzija je **&lt;version&gt;**.
Skupaj me je spravil *DefaltSimon*.

Gif ukaz omogoča **Giphy**</string>
  <string name="INFO_GITHUB">Nanova koda je na voljo na **GitHubu**: https://github.com/DefaltSimon/Nano</string>
  <string name="INFO_INVITE">Hočeš povabiti Nana na svoj server? Super!
**Samo klikni na link:** &lt;link&gt;</string>
  <string name="INFO_REPORT">Prijavi</string>
  <string name="INFO_SUGGESTION">Predlog</string>
  <string name="INFO_SERIES">Serija</string>
  <string name="INFO_CHANNEL">Kanal</string>
  <string name="INFO_SPAM">spama</string>
  <string name="INFO_SWEARING">preklinjanja</string>
  <string name="INFO_INVITE_LINK">povezave za povabilo</string>
  <string name="INFO_CONFIRM">potrjujem</string>
  <string name="INFO_NONE">Nič</string>
  <string name="INFO_RANDOM">naključno</string>
  <string name="INFO_ERROR">napaka</string>
  <string name="INFO_HELP">pomoč</string>
  <string name="ERROR_MISSING_CHANNEL">Kanala nisem našel.</string>
  <string name="ERROR_PREFIX_TOO_LONG">:warning: Predpona je predolga! Meja je 100 znakov.</string>
  <string name="ERROR_NOT_MEMBER">Argument mora biti član</string>
  <string name="ERROR_NO_USER">:warning: Član ne obstaja (kličem izganjalce duhov?).</string>
  <string name="ERROR_NO_USER2">:warning: Tega uporabnika ni.</string>
  <string name="ERROR_MENTION_ONE">Prosim, kliči samo eno osebo naenkrat.</string>
  <string name="ERROR_NO_MENTION">Prosim, kliči (@mention) člana.</string>
  <string name="ERROR_NO_CHMENTION">Prosim, #kliči kanal.</string>
  <string name="ERROR_NO_CHANNEL_MENTION">Prosim, kliči kanal.</string>
  <string name="ERROR_NOT_CHANNEL">Ni kanal.</string>
  <string name="ERROR_INVALID_ROLE_NAME">:warning: Neveljavno ime vloge!</string>
  <string name="ERROR_NOT_NUMBER">Ni številka.</string>
  <string name="ERROR_INVALID_CMD_ARGUMENTS">Nekje se je zalomilo, preveri argumente v ukazu.</string>
  <string name="ERROR_SOMETHING">:warning: Nekaj se je zalomilo...</string>
  <string name="ERROR_NO_SUCH_ROLE">:warning: Vloga ne obstaja!</string>
  <string name="MSG_NUKE_PURGING">Brišem zadnjih {} sporočil (ali sporočila)... :boom:</string>
  <string name="MSG_NUKE_PURGED">Pobrisal sem {} sporočil (ali sporočila) :ok_hand:.</string>
  <string name="MSG_NUKE_OLD">(nekatera sporočila so starejša od 2 tednov, zato jih nisem zbrisal)</string>
  <string name="MSG_KICK_NANO">Ja, pa kaj še :smiley:</string>
  <string name="MSG_BAN_USER">Res hočeš izključiti {}? Potrdi tako, da odgovoriš z/s \'{}\'.</string>
  <string name="MSG_BAN_TIMEOUT">Nisem prejel potrdila. NE bom ga/je izključil :upside_down:</string>
  <string name="MSG_UNBAN_SUCCESS">**{}** je bil/a izključen/a.</string>
  <string name="MSG_SOFTBAN_SUCCESS">{} je bil/a začasno izključen/a zaradi: {}</string>
  <string name="MSG_SOFTBAN_PLSMENTION">Prosim, kliči (@mention) člana, ki ga hočeš začasno izključiti. (samo enega)</string>
  <string name="MSG_SOFTBAN_DELIMIT">:no_entry_sign: Prosim, loči čas in @mention z |</string>
  <string name="MSG_MUTE_LIST">Utišani člani:</string>
  <string name="MSG_MUTE_NONE">Na tem serverju ni utišanih članov.</string>
  <string name="MSG_MUTE_OWNER">:warning: Ne moreš utišati lastnika serverja.</string>
  <string name="MSG_MUTE_SELF">Hočeš utišati samega/o sebe? Malo morgen :rofl:</string>
  <string name="MSG_MUTE_SUCCESS">**{}** zdaj ne more govoriti tukaj. :zipper_mouth:</string>
  <string name="MSG_UNMUTE_SUCCESS">**{}** lahko spet govori tukaj :rofl:</string>
  <string name="MSG_JOIN">Sporočilo ob prihodu na server je bilo posodobljeno :smile:</string>
  <string name="MSG_JOIN_DISABLED">Sporočilo ob prihodu je bilo onemogočeno :white_check_mark:</string>
  <string name="MSG_BAN">Sporočilo ob izključitvi je bilo posodobljeno :smile:</string>
  <string name="MSG_BAN_DISABLED">Sporočilo ob izključitvi je bilo onemogočeno :white_check_mark:</string>
  <string name="MSG_KICK">Sporočilo ob zbrcanju s serverja je bilo posodobljeno :smile:</string>
  <string name="MSG_KICK_DISABLED">Sporočilo ob prisilnem odhodu je bilo onemogočeno :white_check_mark:</string>
  <string name="MSG_LEAVE">Sporočilo po odhodu s serverja je bilo posodobljeno :smile:</string>
  <string name="MSG_LEAVE_DISABLED">Sporočilo ob odhodu je bilo onemogočeno :white_check_mark:</string>
  <string name="MSG_USERINFO_STATUS">Status</string>
  <string name="MSG_USERINFO_MENTION">Klic</string>
  <string name="MSG_USERINFO_ID">Id</string>
  <string name="MSG_USERINFO_TYPE">Vrsta računa</string>
  <string name="MSG_USERINFO_TOPROLE">Najvišja vloga</string>
  <string name="MSG_USERINFO_CREATION">Datum nastanka računa</string>
  <string name="MSG_USERINFO_DATEGOT">Podatki pridobljeni ob {} UTC</string>
  <string name="MSG_USERINFO_USER">**Podatki o uporabniku:**</string>
  <string name="MSG_CMD_WRONG_PARAMS">Neveljavni parametri.
`{}cmd dodaj sprožilo|odziv`</string>
  <string name="MSG_CMD_LIMIT_EXCEEDED">:warning: Dosegel/la si omejitev ukazov po meri ({}).</string>
  <string name="MSG_CMD_NAME_TOO_LONG">:warning: Tvoje ime ukaza je predolgo (največ {}, tvoje je {})</string>
  <string name="MSG_CMD_RESPONSE_TOO_LONG">:warning: Tvoj odgovor na ukaz je predolgo (največ {}, tvoje je {})</string>
  <string name="MSG_CMD_ADDED">Dodan ukaz \'{}\'.</string>
  <string name="MSG_CMD_SEPARATE">:no_entry_sign: Napačni argumenti. Loči ukaz in odgovor s |</string>
  <string name="MSG_CMD_NO_SUCH_COMMAND">:warning: Nisem mogel odstraniti ukaza (ker ne obstaja)</string>
  <string name="MSG_CMD_NO_CUSTOM">Na tem serverju ni ukazov po meri. Dodaš jih tako: `{}cmd dodaj sprožilo|odziv`!</string>
  <string name="MSG_CMD_LIST">Ukazi po meri: (stran **{}**/{})
```{}```</string>
  <string name="MSG_CMD_REMOVE_FAIL">:warning: Ni bilo mogoče odstraniti ukaza (ker ne obstaja)</string>
  <string name="MSG_CMD_LIST_TOO_LONG">Tvoji ukazi so predolgi, da bi jih prikazal. Raje jih nekaj zbriši ali prosi lastnika bota, naj jih zbriše zate, če si ukaze pozabil/a.</string>
  <string name="MSG_CMD_STATUS">Imaš **{}** od *{}* ukazov po meri (*{}%*)</string>
  <string name="MSG_LANG_LIST">Možni jeziki:
{}

Prosim, imej v mislih, da ta funkcija še ni čisto tipi-topi in nekateri prevodi lahko manjkajo. Pa še to! Sporočila pri ukazu \"!help\" niso prevedena.</string>
  <string name="MSG_LANG_NOT_AVAILABLE">Ta prevod ni na voljo. :cry:</string>
  <string name="MSG_LANG_SET">Jezik je bil nastavljen na **{}**. {}</string>
  <string name="MSG_LANG_TRANS">(prevajalci: {})</string>
  <string name="MSG_LANG_CURRENT">Trenutno uporabljaš `{}` ({}), ampak to ti je verjetno že jasno :stuck_out_tongue:
Če hočeš pogledati seznam jezikov, vtipkaj `{}language list`.</string>
  <string name="MSG_SETTINGS_WRONG_USAGE">Nepravilna uporaba, preberi `{}help nano.settings`.</string>
  <string name="MSG_SETTINGS_NOT_TEXT">Dnevniški kanal ne more biti glasovni kanal! Ne bo šlo, majster :smile:</string>
  <string name="MSG_SETTINGS_LOGCHANNEL_SET">Dnevniški kanal nastavljen na **{}** :smile:</string>
  <string name="MSG_SETTINGS_SELFROLE_DISABLED">:ok: Lastna vloga onemogočena.</string>
  <string name="MSG_SETTINGS_SELFROLE_INACCESSIBLE">:warning: **{}** je nedosegljiv (lahko je višje od Nanovih vlog ali pa Nano nima dovoljenja \'Upravljanje vlog\')</string>
  <string name="MSG_SETTINGS_SELFROLE_SET">:ok: Lastna vloga nastavljena na **{}**.</string>
  <string name="MSG_SETTINGS_DEFCHAN_SET">:ok: Privzeti kanal nastavljen na **{}**.</string>
  <string name="MSG_SETTINGS_DEFCHAN_RESET">:ok: Privzeti kanal nastavljen nazaj na privzeto - **{}**.</string>
  <string name="MSG_SETTINGS_WORD">Filter besed {}</string>
  <string name="MSG_SETTINGS_SPAM">Filter spama {}</string>
  <string name="MSG_SETTINGS_INVITE">Filter povabil {}</string>
  <string name="MSG_SETTINGS_NOT_A_SETTING">**{}** ni nastavitev. Na voljo imaš: logchannel, selfrole, invitefilter, wordfilter, spamfilter, defaultchannel.</string>
  <string name="MSG_SETTINGS_NO_BLACKLIST">Ni črnih list</string>
  <string name="MSG_SETTINGS_DISPLAY">**Nastavitve za trenutni server:**```
Omejeni kanali: {}
Filter spama: {}
Filter besed: {}
Odstranitev povabil: {}
Dnevniški kanal: {}
Privzeti kanal: {}
Predpona: {}
Lastna vloga: {}```
Sporočila:
➤ ob prihodu: `{}`
➤ ob odhodu: `{}`
➤ ob izključitvi: `{}`
➤ ob izgonu s serverja: `{}`</string>
  <string name="MSG_BLACKLIST_ADDED">Uspešno dodal &lt;#{}&gt; na črno listo :ok_hand:</string>
  <string name="MSG_BLACKLIST_REMOVED">Črna lista kanalov za {} odstranjena :ok_hand:</string>
  <string name="MSG_BLACKLIST_REMOVE_FAIL">Omejenega kanala nisem mogel odstraniti, ker ni kanala s tem imenom.</string>
  <string name="MSG_BLACKLIST_LIST">Omejeni kanali:
{}</string>
  <string name="MSG_BLACKLIST_NONE">Na tem serverju ni omejenih kanalov. :smile:</string>
  <string name="MSG_RESET_CONFIRM">:warning: Si prepričan/a, da želiš ponastaviti vse Nanove nastavitve na privzeto? Potrdi tako, da napišeš \'{}\'.</string>
  <string name="MSG_RESET_CONFIRM_TIMEOUT">Potrditve nisem sprejel, NE ponastavljam :upside_down:</string>
  <string name="MSG_RESET_DONE">Ponastavitev. :white_check_mark:</string>
  <string name="MSG_PREFIX_CHANGED">Predpona je bila spremenjena v {} :ok_hand:</string>
  <string name="MSG_SETUP_TIMEOUT">Zmanjkalo ti je časa :upside_down: (samo, da veš - časa imaš 35 sekund)</string>
  <string name="MSG_SETUP_WELCOME">**NAMESTITEV SERVERJA**
Začel/a si namestitev serverja. Sestavljena je iz nekaj korakov, pri katerih boš moral/a odgovarjati. Ker si ti začel/a namestitev, bodo veljali samo tvoji odgovori.
**Pa začnimo, a ne?**</string>
  <string name="MSG_SETUP_RESET">Si želel/a ponastaviti vse nastavitve na tem serverju, ki se tičejo bota?
(Tudi zaščito pred spamom in preklinjanjem, seznam adminov, omejene kanale,
dnevniški kanal, predpono, pozdrav in sporočilo ob izključitvi ter prisilnem odhodu). **{} / {}**</string>
  <string name="MSG_SETUP_PREFIX">Katero predpono želiš uporabljati za vse ukaze?
Napiši predpono.
(en primer je: **!** \',torej nastane\' `!help`, `!ping`, ...)</string>
  <string name="MSG_SETUP_JOINMSG">Kaj želiš, da rečem, ko se nekdo pridruži serverju?
Odgovori s tem sporočilom, oz. napiši Nič, če nočeš, da se oglašam.
(:user se bo spremenil v @ime novega uporabnika; recimo -&gt; :user, dobrodošel na server!)</string>
  <string name="MSG_SETUP_SPAM">Hočeš, da filtriram spam? **{} / {}**</string>
  <string name="MSG_SETUP_SWEARING">Hočeš, da filtriram kletvice? **{} / {}**</string>
  <string name="MSG_SETUP_LOGCHANNEL">Kateri kanal naj uporabim za beleženje dnevnika? **ime kanala/{}**</string>
  <string name="MSG_SETUP_LOGCHANNEL_DISABLED">Beleženje dnevnika je bilo onemogočeno.</string>
  <string name="MSG_SETUP_LOGCHANNEL_SET">Dnevniški kanal je bil nastavljen na \'{}\'</string>
  <string name="MSG_SETUP_COMPLETE">**S tem je zaključena osnovna namestitev serverja.**
Po potrebi lahko določiš še nekaj drugih nastavitev:
➤ črna lista kanalov - `nano.blacklist dodaj/odstrani ime_kanala`
➤ sporočilo ob prihodu - `&gt;welcomemsg sporočilo`
➤ sporočilo ob odhodu - `&gt;leavemsg sporočilo`

Predpono lahko čisto lahko spremeniš z `nano.changeprefix prefix`.
Ukazi za admine in moderatorje so dovoljeni samo osebam z vlogami \"Nano Admin\"/\"Nano Mod\".

Ti in vsi admini lahko dodate/odstranite/razvrstite ukaze po meri s `&gt;cmd add/remove/list command|response`.
Za seznam ukazov in njihove razlage uporabi `&gt;cmds`.</string>
  <string name="MSG_PING_MEASURING">Merim...</string>
  <string name="MSG_PING_RESULT">**Pong!** (ribanje: {} ms, reakcija: {} ms)</string>
  <string name="MSG_LOGPOST_SAY">Izveden ukaz {}say</string>
  <string name="MSG_UPTIME">Neutrudno odgovarjam na vprašanja ljudi že **{} dni, {} ur, {} minut in {} sekund!** :open_mouth:</string>
  <string name="MSG_ROLL">{}, ti si vrgel/la {}</string>
  <string name="MSG_DICE">{}, kocka kaže... **{}**</string>
  <string name="MSG_DECIDE_NORMAL">**bobnanje**... Jaz mislim takole: {}</string>
  <string name="MSG_DECIDE_SPECIAL">Veš, kaj? {} je. **ba dum tss.**</string>
  <string name="MSG_DECIDE_NO_ARGS">:grey_exclamation: Navesti moraš vsaj dve možnosti.</string>
  <string name="MSG_8BALL">Čarobna 8-žogca pravi: *{}*.</string>
  <string name="MSG_8BALL_STRINGS">Gotovo je | Skoraj gotovo | Brez dvoma | Zanesi se na to | Verjetno | Da | Vprašaj kasneje | Zdaj ne morem predvideti | Zberi se in zopet vprašaj | Mislim, da ja | JUST DO IT | Moj odgovor je... ne | Moj viri so skeptični | Znamenja kažejo, da ja</string>
  <string name="MSG_AVATAR_OWNERSHIP">Avatar uporabnika **{}**: {}</string>
  <string name="MSG_AVATAR_NONE">**{}** nima avatarja. :expressionless:</string>
  <string name="MSG_SELFROLE_NOT_ENABLED">:warning: Lastna vloga ni omogočena na tem serverju.</string>
  <string name="MSG_SELFROLE_REMOVED">:ok_hand: Odstranil sem **{}** s tvojega seznama vlog.</string>
  <string name="MSG_SELFROLE_ADDED">:ok_hand: Vloga dodana.</string>
  <string name="MSG_AYYLMAO">Moj navdih iz sveta memov.</string>
  <string name="MSG_WHOKNOWS">¯\_(ツ)_/¯</string>
  <string name="MSG_MEME_USAGE">Nepravilna uporaba. Za informacije si oglej _help caption/_help meme.</string>
  <string name="MSG_MEME_NONEXISTENT">Meme ne obstaja. rip</string>
  <string name="MSG_RIP">Rest in pepperoni {}.
`{}` *molitvic do zdaj*...</string>
  <string name="MSG_HELP">**Živjo, jaz sem Nano!**

Za seznam najbolj preprostih ukazov napiši `_help simple`.
Če hočeš bolj podrobno informacijo o ukazu, napiši `_help [ime ukaza]`.
Če si admin/lastnik/lastnica serverja in hočeš namestiti server za Nana, napiši `_setup`.
Priporočljivo je, da se pridružiš \"uradnemu\" Nano serverju, kjer dobiš novice in pomoč: https://discord.gg/FZJB6UJ
P.S.: Eni helperji so tudi Slovenci :wink:</string>
  <string name="MSG_HELP_SIMPLE">`_hello` - Pozdravi tebe ali klicano osebo
`_randomgif` - Objavi naključen gif s strani Giphy
`_roll number` - Zarola naključno številko
`_wiki term` - Ti poda opis besede z Wikipedije
`_urban term` - Ti poda razlago besede z Urban Dictionary (uporaba na lastno odgovornost)
`_decide option|option...` - Se odloči med tvojimi možnostmi, da se tebi ni treba
`_tf item_name` - Cene artiklov s strani backpack.tf
`_steam user_id` - Poišče uporabnike Steama

To je samo nekaj preprostejših ukazov. Za več informacij o vsakem ukazu napiši `_help ukaz`ali `_cmds`, kar te odpelje na wiki stran vseh ukazov.</string>
  <string name="MSG_HELP_CMDWEB">Ukazi in njihove razlage lahko najdeš tukaj: http://nanobot.pw/commands.html</string>
  <string name="MSG_HELP_CMDNOTFOUND">Ukazov nisem našel.
**(Uporaba: `_help [ukaz]`)**</string>
  <string name="MSG_HELP_DESC">Opis</string>
  <string name="MSG_HELP_USE">Uporabi</string>
  <string name="MSG_HELP_ALIASES">Psevdonimi</string>
  <string name="MSG_BUG">Si našel/la hroščka? Prosim, prijavi ga meni (**DefaltSimonu**) na Discord.
Najdeš me tukaj: https://discord.gg/FZJB6UJ</string>
  <string name="MSG_REPORT_EMPTY">Ne moreš oddati praznega poročila.</string>
  <string name="MSG_REPORT_RATELIMIT">Imaš omejitev. Poskusi spet čez 5 minut.</string>
  <string name="MSG_REPORT_THANKS">**Hvala** za tvojo *{}*.</string>
  <string name="MSG_REPORT_R">prijavo</string>
  <string name="MSG_REPORT_S">idejo</string>
  <string name="MSG_IMDB_ERROR">Nekaj se je zalomilo, ko sem poskušal dobiti podatke o filmu.</string>
  <string name="MSG_IMDB_ERROR2">Nekaj ne štima... Poskusim ponovno?</string>
  <string name="MSG_IMDB_ERROR_REPDEV">Nekaj se je zalomilo. Prosim, prijavi to razvijalcu, po možnosti skupaj s sliko zaslona. Hvala!</string>
  <string name="MSG_IMDB_NORESULTS">Ni rezultatov.</string>
  <string name="MSG_IMDB_CANTPERSON">Ne moreš dobiti zgodbe za osebo :rofl:</string>
  <string name="MSG_IMDB_PLOT">Zgodba za **{}**
```{}```</string>
  <string name="MSG_IMDB_SERIES">serija</string>
  <string name="MSG_IMDB_PLOT_MISSING">Ta film pa nima opisa zgodbe.</string>
  <string name="MSG_IMDB_GENRES">Žanri: {}</string>
  <string name="MSG_IMDB_AVGRATING">Povprečna ocena: **{}/10**</string>
  <string name="MSG_IMDB_SEASONS">Sezone: **{}**</string>
  <string name="MSG_IMDB_SUMMARY">
Povzetek:
```{}```
</string>
  <string name="MSG_IMDB_POSTER">Poster: {}</string>
  <string name="MSG_IMDB_PERSON_NOT_SUPPORTED">Iskanje oseb še ni podprto.</string>
  <string name="MSG_IMDB_TRAILER">Napovedniki za **{}** na IMDb:

{}</string>
  <string name="MSG_IMDB_TRAILER_MISSING">Ta film nima napovednikov na IMDb.</string>
  <string name="MSG_IMDB_RATINGS">Ocene za **{}**

Ocene uporabnikov na TMDb: __**{}** od 10__</string>
  <string name="MSG_IMDB_RATINGS_MISSING">Kaže, da ta film nima ocen. Hecno.</string>
  <string name="MSG_IMDB_HELP">**TMDb/IMDb pomoč**

`_imdb search [name ali title]`, `_imdb plot [title]`, `_imdb trailer [title]`, `_imdb rating [title]`\"</string>
  <string name="MSG_CAT_FAILED">Nisem našel naključne mačje fotke... :cry:</string>
  <string name="MSG_XKCD_FAILED">Nisem dobil xkcd :cry:</string>
  <string name="MSG_XKCD">XKCD številka {}:</string>
  <string name="MSG_XKCD_NO_SUCH">Taka XKCD številka ne obstaja.</string>
  <string name="MSG_XKCD_FULL_LINK">Povezava: {}</string>
  <string name="MSG_JOKE_FAILED">Nisem dobil pravega heca... :cry:</string>
  <string name="MSG_MC_HELP">**Minecraft**
```css
_mc name/id:meta - išče artikle in prikaže njihove detajle```</string>
  <string name="MSG_MC_NO_ITEMS">**Ni artikla s tem imenom/id**</string>
  <string name="MSG_MC_DETAILS">**{}**```css
Id: {}:{}```</string>
  <string name="MSG_MOD_MSG_DELETED">Sporočilo izbrisano - {}</string>
  <string name="MSG_MOD_SPAM">spama</string>
  <string name="MSG_MOD_SWEARING">preklinjanja</string>
  <string name="MSG_MOD_INVITE">povezave za povabilo</string>
  <string name="MSG_OSU_ERROR">Nekaj se je zalomilo... :thinking:</string>
  <string name="MSG_OSU_DESC">"**Stopnja**: {}
**Položaj**:
    **Globalno**: #{}
    **Država** (**{}**): #{}
Skupno PP: **{}**"</string>
  <string name="MSG_OSU_TOTAL_SC">Skupne točke</string>
  <string name="MSG_OSU_RANKED_SC">Položajne točke</string>
  <string name="MSG_OSU_AVG_ACC">Povprečna natančnost</string>
  <string name="MSG_OSU_TIME">Iskanje je trajalo {} ms</string>
  <string name="MSG_NANO_SLEEP">Nočko! :sleeping:</string>
  <string name="MSG_NANO_WAKE">:wave:</string>
  <string name="MSG_REMINDER_PRIVATE">:alarm_clock: Prosil/a si me, da te spomnim:
```{}```</string>
  <string name="MSG_REMINDER_CHANNEL">:alarm_clock: Čas je po potekel!
```{}```</string>
  <string name="MSG_REMINDER_HELP">"**Pomoč za opomnik**
`_remind me in [sometime]: [message]` - ti pošlje zasebno sporočilo z opomnikom
`_remind here in [sometime]: [message]` - opomni vse v trenutnem kanalu"</string>
  <string name="MSG_REMINDER_WU_ME">Nepravilna uporaba ukaza. Preberi `{}help remind me in`</string>
  <string name="MSG_REMINDER_WU_HERE">Nepravilna uporaba ukaza. Preberi `{}help remind here in`</string>
  <string name="MSG_REMINDER_NO_BRACKETS">Ne uporabljaj **[** in **]** ! Poskusi brez tega.</string>
  <string name="MSG_REMINDER_INVALID_RANGE">Ni veljaven časovni razpon (5 sekund do 2 dni)</string>
  <string name="MSG_REMINDER_SET">Opomnik nastavljen :smile:</string>
  <string name="MSG_REMINDER_NO_PARTIALS">Prosim, ne uporabljaj decimalk, ko zapisuješ minute/ure/dni itd. (na primer \"1.7 days\") - namesto tega uporabi `1d 16h 48min` (da si se pa spravil/a pisat to v decimalke, si pa Bog/inja) :wink:</string>
  <string name="MSG_REMINDER_SOON">**kmalu™**</string>
  <string name="MSG_REMINDER_TIME_LEFT">čez **{}**</string>
  <string name="MSG_REMINDER_LIST_NONE">Nimaš opomnikov.</string>
  <string name="MSG_REMINDER_LIST">Tvoji opomniki:
{}</string>
  <string name="MSG_REMINDER_DELETE_ALL">Vsi opomniki so bili izbrisani.</string>
  <string name="MSG_REMINDER_DELETE_NONE">Ni opomnika s to vsebino.</string>
  <string name="MSG_REMINDER_DELETE_SUCCESS">Opomnik odstranjen.</string>
  <string name="MSG_REMINDER_LIMIT_EXCEEDED">:warning: Presegel/la si maksimalno število opomnikov (**{}** naenkrat)</string>
  <string name="MSG_REMINDER_INVALID_FORMAT">:warning: Neveljaven časovni format, prosim uporabi \"sec\", \"min\", \"h\", \"d\" itd...</string>
  <string name="MSG_STATUS_STATS">Statistika</string>
  <string name="MSG_STATUS_SERVERS">Serverji</string>
  <string name="MSG_STATUS_SERVERS_L">{} serverjev</string>
  <string name="MSG_STATUS_USERS">Uporabniki</string>
  <string name="MSG_STATUS_USERS_L">{} uporabnikov</string>
  <string name="MSG_STATUS_CHANNELS">Kanali</string>
  <string name="MSG_STATUS_CHANNELS_L">{} kanalov</string>
  <string name="MSG_DEBUG_VERSION">Različica Nana</string>
  <string name="MSG_DEBUG_DPY">discord.py</string>
  <string name="MSG_DEBUG_RAM">Poraba RAM</string>
  <string name="MSG_DEBUG_GC">{} MB (počiščenih {} MB spomina)</string>
  <string name="MSG_DEBUG_CPU">Poraba CPU</string>
  <string name="MSG_DEBUG_CPU_L">{} %</string>
  <string name="MSG_DEBUG_REMINDERS">Opomniki v teku</string>
  <string name="MSG_DEBUG_VOTES">Ankete v teku</string>
  <string name="MSG_DEBUG_R_MEM">Spomin na Redisu</string>
  <string name="MSG_DEBUG_R_KEYS">Ključi na Redisu</string>
  <string name="MSG_DEBUG_UPTIME">Čas delovanja</string>
  <string name="MSG_DEBUG_UPTIME_L">{} dni, {}:{}:{}</string>
  <string name="MSG_DEBUG_INFO">**Tehnično čudo:**</string>
  <string name="MSG_STATS_MSGS">Sporočila poslana</string>
  <string name="MSG_STATS_ARGS">Dobljeni napačni argumenti</string>
  <string name="MSG_STATS_PERM">Št. poskusov zlorabe ukazov</string>
  <string name="MSG_STATS_HELP">Št. pomočnikov</string>
  <string name="MSG_STATS_IMG">Št. poslanih slik</string>
  <string name="MSG_STATS_VOTES">Št. dobljenih glasov</string>
  <string name="MSG_STATS_SLEPT">Čas počitka</string>
  <string name="MSG_STATS_PONG">Št. (ping)pongov</string>
  <string name="MSG_STATS_INFO">**Statistika**</string>
  <string name="MSG_PREFIX_OHYEAH">Pa še res je!</string>
  <string name="MSG_PREFIX">Predpona na tem serverju je **{}**</string>
  <string name="MSG_MEMBERS_LIST">*__Člani__*:

{}
</string>
  <string name="MSG_MEMBERS_TOTAL">Skupaj: **{}** članov</string>
  <string name="MSG_MEMBERS_AMOUNT">Ta ceh ima skupaj **{}** članov</string>
  <string name="MSG_SERVER_VL">Potrditvena stopnja</string>
  <string name="MSG_SERVER_VL_NONE">Ni je</string>
  <string name="MSG_SERVER_VL_LOW">Nizka</string>
  <string name="MSG_SERVER_VL_MEDIUM">Srednja</string>
  <string name="MSG_SERVER_VL_HIGH">Visoka (╯°□°）╯︵ ┻━┻</string>
  <string name="MSG_SERVER_ID">"ID: *{}*"</string>
  <string name="MSG_SERVER_DATE_CREATED">Server je bil ustvarjen {}</string>
  <string name="MSG_SERVER_MEMBERS">Člani [{} skupaj]</string>
  <string name="MSG_SERVER_MEMBERS_L">{} prisotni(h)</string>
  <string name="MSG_SERVER_CHANNELS">Kanali [{} skupaj]</string>
  <string name="MSG_SERVER_CHANNELS_L">{} glasovni(h) | {} besedilni(h)</string>
  <string name="MSG_SERVER_ROLES">Vloge</string>
  <string name="MSG_SERVER_ROLES_L">{} po meri</string>
  <string name="MSG_SERVER_OWNER">Lastnik serverja</string>
  <string name="MSG_SERVER_OWNER_L">{}#{} ID:{}</string>
  <string name="MSG_SERVER_INFO">**Podatki o serverju:**</string>
  <string name="MSG_STEAM_INVALID_URL">Prosim, vnesi **konec** (\"skrajšanega\") URL naslova, ne pa *celega* URL-ja, za božjo voljo!</string>
  <string name="MSG_STEAM_PRIVATE">Nekaj se ni izšlo. Uporabnik ima mogoče zaseben profil.</string>
  <string name="MSG_STEAM_PRIVATE_FRIENDS">Nisem dobil seznama prijateljev (uporabnik ima verjetno zasebni profil)</string>
  <string name="MSG_STEAM_PRIVATE_GAMES">Nisem dobil seznama iger (uporabnik ima verjetno zasebni profil)</string>
  <string name="MSG_STEAM_FRIENDS">*Uporabnik:* **{}**

*Prijatelji:* {}</string>
  <string name="MSG_STEAM_GAMES">*Uporabnik:* **{}**:

*Igre v lasti:* {}</string>
  <string name="MSG_STEAM_GAMES_TOO_MANY">Sporočilo ne gre v Discord: **uporabnik ima preveč iger (lol)**</string>
  <string name="MSG_STEAM_FRIENDS_TOO_MANY">Sporočilo ne gre v Discord: **uporabnik ima preveč prijateljev (lol)**</string>
  <string name="MSG_STEAM_USER_INFO">Uporabnik: **{}**
```css
Status: {}
Stopnja: {}
Igre: {} v lasti (upoštevam tudi brezplačne)
Prijatelji: {}```
Neposredna povezava: http://steamcommunity.com/id/{}/</string>
  <string name="MSG_STEAM_ONLINE">Prisotni</string>
  <string name="MSG_STEAM_OFFLINE">Odsotni</string>
  <string name="MSG_STEAM_HELP">**Ukazi za Steam:**
`_steam user community_url`, `_steam friends community_url`, `_steam games community_url`</string>
  <string name="MSG_TF_UNAVAILABLE">Ta ukaz trenutno ni na voljo. Sorči.</string>
  <string name="MSG_TF_NO_SUCH_ITEM">Trenutno ne najdem *nobenega artikla* s tem imenom.</string>
  <string name="MSG_TF_LIST">**{}** *(on bp.tf)*

{}</string>
  <string name="MSG_VOTING_NO_PROGRESS">:warning: Trenutno ne poteka nobeno glasovanje.</string>
  <string name="MSG_VOTING_IN_PROGRESS">:warning: Glasovanje že poteka.</string>
  <string name="MSG_VOTING_I_USAGE">Nepravilna uporaba (Naslov obdaj z **\"**).
Za več informacij poglej pod `{}help vote start`.</string>
  <string name="MSG_VOTING_NO_TITLE">Prosim navedi naslov.</string>
  <string name="MSG_VOTING_STARTED">Glasovanje se je začelo:
**{}**
```js
{}```</string>
  <string name="MSG_VOTING_AMOUNT">Skupaj je glasovalo {} ljudi</string>
  <string name="MSG_VOTING_AMOUNT2">{} glasov</string>
  <string name="MSG_VOTING_ENDED">**Glasovanje končano:**</string>
  <string name="MSG_VOTING_ERROR">Nekaj se je zalomilo, ko sem poskusil zaključiti glasovanje.</string>
  <string name="MSG_VOTING_OPTIONS_TM">:warning: Preveč možnosti (dovolim največ **{}**, ti si jih dal/a pa kar *{}*)</string>
  <string name="MSG_VOTING_OPTIONS_TL">:warning: Vse skupaj je čisto predolgo! (največja dolžina je {}, tvoja reč jih ima {})</string>
  <string name="MSG_VOTING_S_NONE">nihče še ni glasoval</string>
  <string name="MSG_VOTING_S_ONE">samo ena oseba je glasovala</string>
  <string name="MSG_VOTING_S_MULTI">{} ljudi (ali alienov) je glasovalo</string>
  <string name="MSG_VOTING_STATUS">**Glasovanje:** \"{}\"
```Do zdaj {}.```</string>
  <string name="MSG_VOTING_NOT_NUMBER">Argument za glasovanje mora biti številka.</string>
  <string name="MSG_VOTING_CHEATER">Ti-ti, goljuf(ica) :smiley:</string>
  <string name="MSG_VOTING_SOMETHING_WRONG">Nekaj ne štima... :frowning2:</string>
  <string name="MSG_WIKI_QUERY_TOO_LONG">Poizvedba je predolga: največ 300 znakov (tvoja poizvedba jih ima {})</string>
  <string name="MSG_WIKI_NO_QUERY">Prosim, vnesi besedo, ki jo hočeš definirati.</string>
  <string name="MSG_WIKI_NO_DEF">Ne najdem definicije.</string>
  <string name="MSG_WIKI_MULTIPLE_DEF">Dobil sem več definicij za {}, prosim bodi bolj specifičen/na (ne vprašaj, kako - jaz sem samo navaden bot).</string>
  <string name="MSG_URBAN_DEF_TOO_LONG">Definicija je dolga ko čreva - ne morem je prikazati!</string>
  <string name="EVENT_JOIN">je prišel</string>
  <string name="EVENT_LEAVE">je odšel</string>
  <string name="EVENT_BAN">je bil izključen</string>
  <string name="EVENT_SERVER_JOIN">**Živjo!** Jaz sem Nano!
Zdaj, ko me imaš na serverju, bi mogoče rad/a nastavil/a stvar ali dve. Trenutno lahko omejene ukaze uporablja samo lastnik serverja. Ampak brez panike, tudi drugim lahko omogočiš njihovo uporabo - samo dodaj jim vlogo \"Nano Admin\"!

Za najbolj osnovno namestitev napiši `!setup` (če si lastnik/ca serverja). Tako boš lahko nastavil/a nekaj lažjih reči.
Ko si končal/a s tem, lahko napišeš `!cmds` in si ogledaš vse moje ukaze.


Priporočam še, da prideš na \"uraden\" Nanov server, kjer dobiš novice in pomoč: https://discord.gg/FZJB6UJ (Ne grizemo)</string>
</resources>
